napari_sim_simulator/__init__.py
napari_sim_simulator/_reader.py
napari_sim_simulator/_sample_data.py
napari_sim_simulator/_widget.py
napari_sim_simulator/_writer.py
napari_sim_simulator/napari.yaml
napari_sim_simulator/_tests/__init__.py
napari_sim_simulator/_tests/test_reader.py
napari_sim_simulator/_tests/test_sample_data.py
napari_sim_simulator/_tests/test_widget.py
napari_sim_simulator/_tests/test_writer.py
napari_sim_SIMulator-0.0.1.dist-info/LICENSE
napari_sim_SIMulator-0.0.1.dist-info/METADATA
napari_sim_SIMulator-0.0.1.dist-info/WHEEL
napari_sim_SIMulator-0.0.1.dist-info/entry_points.txt
napari_sim_SIMulator-0.0.1.dist-info/top_level.txt
napari_sim_SIMulator-0.0.1.dist-info/RECORD
