Metadata-Version: 2.1
Name: napari-sim-SIMulator
Version: 0.0.1
Summary: A simple plugin to simulate raw image stacks for structured illumination microscopy (SIM).
Home-page: https://github.com/Meizhu-Liang/napari-sim-SIMulator
Author: Meizhu Liang
Author-email: ml2618@ic.ac.uk
License: BSD-3-Clause
Project-URL: Bug Tracker, https://github.com/Meizhu-Liang/napari-sim-SIMulator/issues
Project-URL: Documentation, https://github.com/Meizhu-Liang/napari-sim-SIMulator#README.md
Project-URL: Source Code, https://github.com/Meizhu-Liang/napari-sim-SIMulator
Project-URL: User Support, https://github.com/Meizhu-Liang/napari-sim-SIMulator/issues
Classifier: Development Status :: 2 - Pre-Alpha
Classifier: Framework :: napari
Classifier: License :: OSI Approved :: BSD License
Classifier: Operating System :: OS Independent
Classifier: Programming Language :: Python
Classifier: Programming Language :: Python :: 3
Classifier: Programming Language :: Python :: 3.8
Classifier: Programming Language :: Python :: 3.9
Classifier: Programming Language :: Python :: 3.10
Requires-Python: >=3.8
License-File: LICENSE
Requires-Dist: numpy
Requires-Dist: magicgui
Requires-Dist: qtpy
Provides-Extra: testing
Requires-Dist: tox ; extra == 'testing'
Requires-Dist: pytest ; extra == 'testing'
Requires-Dist: pytest-cov ; extra == 'testing'
Requires-Dist: pytest-qt ; extra == 'testing'
Requires-Dist: napari ; extra == 'testing'
Requires-Dist: pyqt5 ; extra == 'testing'
